{"name":"build-javascript","namedChunkGroups":{"polyfill":{"name":"polyfill","assets":[{"name":"webpack-runtime-406d5d4fbb2f9d5da188.js","size":5362},{"name":"polyfill-635a9dfd597478a1f0fa.js","size":85862}],"filteredAssets":0,"assetsSize":91224,"filteredAuxiliaryAssets":2,"auxiliaryAssetsSize":228580},"app":{"name":"app","assets":[{"name":"webpack-runtime-406d5d4fbb2f9d5da188.js","size":5362},{"name":"framework-6bdc9aaa9caa3de6408b.js","size":129775},{"name":"app-4fe08dd71722f533555d.js","size":107112}],"filteredAssets":0,"assetsSize":242249,"filteredAuxiliaryAssets":3,"auxiliaryAssetsSize":779656},"component---src-pages-404-js":{"name":"component---src-pages-404-js","assets":[{"name":"styles.457773932d52d28da380.css","size":5414},{"name":"commons-4a618a8fb50b4861a7f2.js","size":16807},{"name":"component---src-pages-404-js-b9c73eb3040053d5ad0e.js","size":485}],"filteredAssets":0,"assetsSize":22706,"filteredAuxiliaryAssets":2,"auxiliaryAssetsSize":70741},"component---src-pages-index-js":{"name":"component---src-pages-index-js","assets":[{"name":"styles.457773932d52d28da380.css","size":5414},{"name":"commons-4a618a8fb50b4861a7f2.js","size":16807},{"name":"component---src-pages-index-js-724ab68db4d8cee4eb19.js","size":2600}],"filteredAssets":0,"assetsSize":24821,"filteredAuxiliaryAssets":2,"auxiliaryAssetsSize":71788},"component---src-pages-page-2-js":{"name":"component---src-pages-page-2-js","assets":[{"name":"styles.457773932d52d28da380.css","size":5414},{"name":"commons-4a618a8fb50b4861a7f2.js","size":16807},{"name":"component---src-pages-page-2-js-43b778637abe228439c4.js","size":522}],"filteredAssets":0,"assetsSize":22743,"filteredAuxiliaryAssets":2,"auxiliaryAssetsSize":70842},"component---src-pages-prismic-pages-uid-js":{"name":"component---src-pages-prismic-pages-uid-js","assets":[{"name":"styles.457773932d52d28da380.css","size":5414},{"name":"commons-4a618a8fb50b4861a7f2.js","size":16807},{"name":"component---src-pages-prismic-pages-uid-js-a36e0ab99510b45ed30b.js","size":559}],"filteredAssets":0,"assetsSize":22780,"filteredAuxiliaryAssets":2,"auxiliaryAssetsSize":71277},"component---src-pages-using-ssr-js":{"name":"component---src-pages-using-ssr-js","assets":[{"name":"styles.457773932d52d28da380.css","size":5414},{"name":"commons-4a618a8fb50b4861a7f2.js","size":16807},{"name":"component---src-pages-using-ssr-js-7d72e85504b244c87028.js","size":879}],"filteredAssets":0,"assetsSize":23100,"filteredAuxiliaryAssets":2,"auxiliaryAssetsSize":71908},"component---src-pages-using-typescript-tsx":{"name":"component---src-pages-using-typescript-tsx","assets":[{"name":"styles.457773932d52d28da380.css","size":5414},{"name":"commons-4a618a8fb50b4861a7f2.js","size":16807},{"name":"component---src-pages-using-typescript-tsx-442a9618757535247250.js","size":1332}],"filteredAssets":0,"assetsSize":23553,"filteredAuxiliaryAssets":2,"auxiliaryAssetsSize":72232},"component---src-templates-using-dsg-js":{"name":"component---src-templates-using-dsg-js","assets":[{"name":"styles.457773932d52d28da380.css","size":5414},{"name":"commons-4a618a8fb50b4861a7f2.js","size":16807},{"name":"component---src-templates-using-dsg-js-b33b6dc2af78cd8a7049.js","size":795}],"filteredAssets":0,"assetsSize":23016,"filteredAuxiliaryAssets":2,"auxiliaryAssetsSize":71197}},"assetsByChunkName":{"polyfill":["webpack-runtime-406d5d4fbb2f9d5da188.js","polyfill-635a9dfd597478a1f0fa.js"],"app":["webpack-runtime-406d5d4fbb2f9d5da188.js","framework-6bdc9aaa9caa3de6408b.js","app-4fe08dd71722f533555d.js"],"component---src-pages-404-js":["styles.457773932d52d28da380.css","commons-4a618a8fb50b4861a7f2.js","component---src-pages-404-js-b9c73eb3040053d5ad0e.js"],"component---src-pages-index-js":["styles.457773932d52d28da380.css","commons-4a618a8fb50b4861a7f2.js","component---src-pages-index-js-724ab68db4d8cee4eb19.js"],"component---src-pages-page-2-js":["styles.457773932d52d28da380.css","commons-4a618a8fb50b4861a7f2.js","component---src-pages-page-2-js-43b778637abe228439c4.js"],"component---src-pages-prismic-pages-uid-js":["styles.457773932d52d28da380.css","commons-4a618a8fb50b4861a7f2.js","component---src-pages-prismic-pages-uid-js-a36e0ab99510b45ed30b.js"],"component---src-pages-using-ssr-js":["styles.457773932d52d28da380.css","commons-4a618a8fb50b4861a7f2.js","component---src-pages-using-ssr-js-7d72e85504b244c87028.js"],"component---src-pages-using-typescript-tsx":["styles.457773932d52d28da380.css","commons-4a618a8fb50b4861a7f2.js","component---src-pages-using-typescript-tsx-442a9618757535247250.js"],"component---src-templates-using-dsg-js":["styles.457773932d52d28da380.css","commons-4a618a8fb50b4861a7f2.js","component---src-templates-using-dsg-js-b33b6dc2af78cd8a7049.js"]},"childAssetsByChunkName":{}}